oslislim/__init__.py
oslislim/crypto_client.py
oslislim/exceptions.py
oslislim-0.3.2.dist-info/licenses/LICENSE
oslislim-0.3.2.dist-info/METADATA
oslislim-0.3.2.dist-info/WHEEL
oslislim-0.3.2.dist-info/entry_points.txt
oslislim-0.3.2.dist-info/top_level.txt
oslislim-0.3.2.dist-info/RECORD
